chert/__init__.py
chert/atom.xml
chert/cli.py
chert/core.py
chert/fal.py
chert/hypertext.py
chert/log.py
chert/parsers.py
chert/rss.xml
chert/utils.py
chert/version.py
chert/scaffold/.gitignore
chert/scaffold/LICENSE
chert/scaffold/README.md
chert/scaffold/TODO.md
chert/scaffold/chert.yaml
chert/scaffold/custom.py
chert/scaffold/entries/about.md
chert/scaffold/entries/colophon.md
chert/scaffold/entries/new_post.md
chert/scaffold/themes/sedimental/LICENSE
chert/scaffold/themes/sedimental/README.md
chert/scaffold/themes/sedimental/archive_brief.html
chert/scaffold/themes/sedimental/base.html
chert/scaffold/themes/sedimental/content.html
chert/scaffold/themes/sedimental/content.md
chert/scaffold/themes/sedimental/entry.html
chert/scaffold/themes/sedimental/entry.md
chert/scaffold/themes/sedimental/css/github.css
chert/scaffold/themes/sedimental/css/normalize.css
chert/scaffold/themes/sedimental/css/sedimental.css
chert/scaffold/themes/sedimental/css/skeleton.css
chert/scaffold/themes/sedimental/img/by-sa.png
chert/scaffold/themes/sedimental/img/favicon.png
chert/scaffold/themes/sedimental/img/favicon_grayscale.png
chert/scaffold/themes/sedimental/img/feed.png
chert/scaffold/themes/sedimental/js/lol.js
chert/scaffold/uploads/myphoto.png
chert-24.0.0.dist-info/LICENSE
chert-24.0.0.dist-info/METADATA
chert-24.0.0.dist-info/WHEEL
chert-24.0.0.dist-info/entry_points.txt
chert-24.0.0.dist-info/top_level.txt
chert-24.0.0.dist-info/RECORD
