Metadata-Version: 2.1
Name: chert
Version: 24.0.0
Summary: Sharp and sparky static-site generation.
Home-page: https://github.com/mahmoud/chert
Author: Mahmoud Hashemi
Author-email: mahmoud@hatnote.com
License: BSD
Platform: any
Classifier: Development Status :: 4 - Beta
Classifier: Environment :: Console
Classifier: Intended Audience :: Developers
Classifier: Topic :: Internet :: WWW/HTTP
Classifier: Operating System :: OS Independent
Classifier: Programming Language :: Python :: 3.10
Classifier: Programming Language :: Python :: 3.11
Classifier: Programming Language :: Python :: 3.12
Classifier: Programming Language :: Python :: 3.13
License-File: LICENSE
Requires-Dist: Markdown>=3.1
Requires-Dist: PyYAML>=5.1.0
Requires-Dist: ashes>=19.2.0
Requires-Dist: boltons>=20.0.0
Requires-Dist: face>=20.1.1
Requires-Dist: html5lib>=1.0.1
Requires-Dist: hyperlink>=18.0.0
Requires-Dist: lithoxyl>=21.0.0
Requires-Dist: python-dateutil>=2.8.0
